{
	"description": "项目配置文件。",
	"setting": {
		"urlCheck": false,
		"es6": true,
		"postcss": true,
		"minified": true,
		"newFeature": true,
		"nodeModules": true
	},
	"compileType": "game",
	"libVersion": "game",
	"appid": "wxe92f989fbfee04f6",
	"projectname": "birdHunt",
	"condition": {
		"search": {
			"current": -1,
			"list": []
		},
		"conversation": {
			"current": -1,
			"list": []
		},
		"game": {
			"list": [],
			"current": -1
		},
		"miniprogram": {
			"current": -1,
			"list": []
		}
	}
}